src/tiny_risc.svh
`ifndef RISCV32_SVH
`define RISCV32_SVH

// ------------------------------------------------------------------
// 1. 基本設定 (データ幅とレジスタ本数)
// ------------------------------------------------------------------
`define DATA_WIDTH 32
`define REG_WIDTH 5
`define ALU_CONTROL_WIDTH 4
`define RESULT_SRC_WIDTH 2
`define OPCODE_WIDTH 7
`define FUNCT3_WIDTH 3
`define FUNCT7_WIDTH 7

// ------------------------------------------------------------------
// 2. RISC-V 命令 Opcode (7-bit: inst[6:0])
// ------------------------------------------------------------------
`define OPCODE_LOAD 7'b0000011 // LW, LH, LB (I-type Load)
`define OPCODE_I_TYPE 7'b0010011 // ADDI, SLLI, SRLI, SRAI (I-type Arith)
`define OPCODE_AUIPC 7'b0010111 // AUIPC (U-type)
`define OPCODE_STORE 7'b0100011 // SW, SH, SB (S-type Store)
`define OPCODE_R_TYPE 7'b0110011 // ADD, SUB, SLT, XOR, etc. (R-type)
`define OPCODE_LUI 7'b0110111 // LUI (U-type)
`define OPCODE_BRANCH 7'b1100011 // BEQ, BNE, BLT, BGE, etc. (B-type)
`define OPCODE_JALR 7'b1100111 // JALR (I-type Jump)
`define OPCODE_JAL 7'b1101111 // JAL (J-type Jump)
`define OPCODE_SYSTEM 7'b1110011 // ECALL, EBREAK, CSRR* (I-type System)

// ------------------------------------------------------------------
// 3. RISC-V Funct3 (3-bit: inst[14:12])
// ------------------------------------------------------------------
// R-Type & I-Type (共通・演算)
`define FUNCT3_ADD_SUB 3'b000    // ADD / SUB (R-Type)
`define FUNCT3_ADDI 3'b000    // ADDI (I-Type)
`define FUNCT3_SLL 3'b001    // SLL (R-Type)
`define FUNCT3_SLLI 3'b001    // SLLI (I-Type)
`define FUNCT3_SLT 3'b010    // SLT (R-Type)
`define FUNCT3_SLTI 3'b010    // SLTI (I-Type)
`define FUNCT3_SLTU 3'b011    // SLTU (R-Type)
`define FUNCT3_SLTIU 3'b011    // SLTIU (I-Type)
`define FUNCT3_XOR 3'b100    // XOR (R-Type)
`define FUNCT3_XORI 3'b100    // XORI (I-Type)
`define FUNCT3_SHIFT     3'b101    // SRL / SRA / SRLI / SRAI 用共通デコードプレースホルダ
`define FUNCT3_SRL_SRA 3'b101    // SRL / SRA (R-Type)
`define FUNCT3_SRAI_SRLI 3'b101    // SRAI / SRLI (I-Type)
`define FUNCT3_OR 3'b110    // OR (R-Type)
`define FUNCT3_ORI 3'b110    // ORI (I-Type)
`define FUNCT3_AND 3'b111    // AND (R-Type)
`define FUNCT3_ANDI 3'b111    // ANDI (I-Type)

// B-Type (Branch)
`define FUNCT3_BEQ 3'b000    // BEQ
`define FUNCT3_BNE 3'b001    // BNE
`define FUNCT3_BLT 3'b100    // BLT
`define FUNCT3_BGE 3'b101    // BGE
`define FUNCT3_BLTU 3'b110    // BLTU
`define FUNCT3_BGEU 3'b111    // BGEU

// ------------------------------------------------------------------
// 4. RISC-V Funct7 (7-bit: inst[31:25])
// ------------------------------------------------------------------
`define FUNCT7_ADD_SLL_SRL 7'b0000000 // ADD, SLL, SRL (R-type)
`define FUNCT7_SUB_SRA 7'b0100000 // SUB, SRA (R-type / I-type shift)
`define FUNCT7_SUB 7'b0100000 // SUB 判定用
`define FUNCT7_SRA 7'b0100000 // SRA 判定用

// ------------------------------------------------------------------
// 5. ALU 制御コード (4-bit, 制御ユニットが出力)
// ------------------------------------------------------------------
// 演算命令
`define ALU_ADD 4'h0
`define ALU_SUB 4'h1
`define ALU_AND 4'h2
`define ALU_OR 4'h3
`define ALU_XOR 4'h4
`define ALU_SLL 4'h5
`define ALU_SRL 4'h6
`define ALU_SRA 4'h7
`define ALU_SLT 4'h8
`define ALU_SLTU 4'h9
`define ALU_LUI 4'hA

// 分岐比較 (Branch)
// BEQ/BNE/BLT/BGE 命令の実行に必要な比較指示
`define BR_BEQ 4'hA // Branch Equal (A == B)
`define BR_BNE 4'hB // Branch Not Equal (A != B)
`define BR_BLT 4'hC // Branch Less Than Signed (A <s B)
`define BR_BGE 4'hD // Branch Greater Than or Equal Signed (A >=s B)
`define BR_BLTU 4'hE // Branch Less Than Unsigned (A <u B)
`define BR_BGEU 4'hF // Branch Greater Than or Equal Unsigned (A >=u B)

// ------------------------------------------------------------------
// 6. Write Back Data Source (ResultSrc: 2-bit)
// ------------------------------------------------------------------
`define RESULT_SRC_ALU 2'b00  // ALUの結果を書き込む (デフォルト)
`define RESULT_SRC_MEM 2'b01  // メモリからの読み出しデータを書き込む (Load命令用)
`define RESULT_SRC_PC4 2'b10  // PC+4の値を書き込む (JAL命令用)

`define RESULT_ALU 2'b00  // RESULT_SRC_ALU と同等 (別名)
`define RESULT_MEM 2'b01  // RESULT_SRC_MEM と同等 (別名)
`define RESULT_PC4 2'b10  // RESULT_SRC_PC4 と同等 (別名)
// 2'b11 は未定義/予約

`endif  // RISCV32_SVH

src/control.sv
// ====================================================================
// Module: control
// Description: Decodes instruction opcodes, funct3, and funct7 elements.
//              Generates datapath selection flags and ALU operations.
// ====================================================================

`default_nettype none
`include "tiny_risc.svh"

module control (
    input logic [6:0] opcode,
    input logic [2:0] funct3,
    input logic [6:0] funct7,

    output logic       reg_write,
    output logic       alu_src,
    output logic [1:0] mem_to_reg,  // 00: ALU, 01: Mem, 10: PC+4
    output logic       mem_write,
    output logic       mem_read,
    output logic       branch,
    output logic       jump,
    output logic [3:0] alu_control
);

    logic funct7_5;

    assign funct7_5 = funct7[5];

    // Single-cycle main control decoder logic
    always_comb begin
        // Setup sensible defaults in lower_case
        reg_write   = 1'b0;
        alu_src     = 1'b0;
        mem_to_reg  = 2'b00;
        mem_write   = 1'b0;
        mem_read    = 1'b0;
        branch      = 1'b0;
        jump        = 1'b0;
        alu_control = `ALU_ADD;

        case (opcode)
            // R-Type operations (ADD, SUB, AND, OR, XOR, shifts etc.)
            7'b0110011: begin
                reg_write  = 1'b1;
                alu_src    = 1'b0;
                mem_to_reg = 2'b00;

                // Select custom operation depending on funct3 & funct7
                case (funct3)
                    `FUNCT3_ADD_SUB:
                    alu_control = (funct7_5) ? `ALU_SUB : `ALU_ADD;
                    `FUNCT3_SLL: alu_control = `ALU_SLL;
                    `FUNCT3_SLT: alu_control = `ALU_SLT;
                    `FUNCT3_SLTU: alu_control = `ALU_SLTU;
                    `FUNCT3_XOR: alu_control = `ALU_XOR;
                    `FUNCT3_SRL_SRA:
                    alu_control = (funct7_5) ? `ALU_SRA : `ALU_SRL;
                    `FUNCT3_OR: alu_control = `ALU_OR;
                    `FUNCT3_AND: alu_control = `ALU_AND;
                    default: alu_control = `ALU_ADD;
                endcase
            end

            // I-Type ALU operations (ADDI, ANDI, ORI, XORI etc.)
            7'b0010011: begin
                reg_write  = 1'b1;
                alu_src    = 1'b1;
                mem_to_reg = 2'b00;

                case (funct3)
                    `FUNCT3_ADDI: alu_control = `ALU_ADD;
                    `FUNCT3_SLLI: alu_control = `ALU_SLL;
                    `FUNCT3_SLTI: alu_control = `ALU_SLT;
                    `FUNCT3_SLTIU: alu_control = `ALU_SLTU;
                    `FUNCT3_XORI: alu_control = `ALU_XOR;
                    `FUNCT3_SRAI_SRLI:
                    alu_control = (funct7[5]) ? `ALU_SRA : `ALU_SRL; // SRAI / SRLI
                    `FUNCT3_ORI: alu_control = `ALU_OR;  // ORI
                    `FUNCT3_ANDI: alu_control = `ALU_AND;  // ANDI
                    default: alu_control = `ALU_ADD;
                endcase
            end

            // I-Type Load operations (LW, LB, LH, LBU, LHU)
            `OPCODE_LOAD: begin
                reg_write  = 1'b1;
                alu_src    = 1'b1;
                mem_to_reg = 2'b01; // Write-back memory contents
                mem_read   = 1'b1;
                alu_control = `ALU_ADD; // Node offset addition
            end

            // S-Type Store operations (SW, SB, SH)
            `OPCODE_STORE: begin
                reg_write  = 1'b0;
                alu_src    = 1'b1;
                mem_write  = 1'b1;
                alu_control = `ALU_ADD; // Address addition
            end

            // B-Type Branch instructions (BEQ, BNE, BLT, BGE)
            `OPCODE_BRANCH: begin
                reg_write = 1'b0;
                alu_src   = 1'b0;
                branch    = 1'b1;

                case (funct3)
                    `FUNCT3_BEQ:
                    alu_control = `ALU_SUB;  // BEQ (uses sub zero check)
                    `FUNCT3_BNE:
                    alu_control = `ALU_SUB;  // BNE (uses sub zero check)
                    `FUNCT3_BLT:
                    alu_control = `ALU_SLT;  // BLT (uses signed comparison)
                    `FUNCT3_BGE:
                    alu_control = `ALU_SLT;  // BGE (uses signed comparison)
                    `FUNCT3_BLTU:
                    alu_control = `ALU_SLTU;  // BLTU (uses unsigned comparison)
                    `FUNCT3_BGEU:
                    alu_control = `ALU_SLTU;  // BGEU (uses unsigned comparison)
                    default: alu_control = `ALU_SUB;
                endcase
            end

            // J-Type JAL jump
            `OPCODE_JAL: begin
                reg_write = 1'b1;
                mem_to_reg = 2'b10; // PC + 4 written to link register standard x1 (ra)
                jump = 1'b1;
            end

            // I-Type JALR jump
            `OPCODE_JALR: begin
                reg_write   = 1'b1;
                alu_src     = 1'b1;
                mem_to_reg  = 2'b10;  // PC + 4 written to link register
                jump        = 1'b1;
                alu_control = `ALU_ADD;
            end

            // U-Type LUI loading
            `OPCODE_LUI: begin
                reg_write  = 1'b1;
                alu_src    = 1'b1;
                mem_to_reg = 2'b00;
                // Immediate value shifted left will be routed straight through ALU
                alu_control = 4'b1010; // Passthrough logic or customized add
            end

            default: begin
                // Secure unknown operations
                reg_write   = 1'b0;
                alu_control = `ALU_ADD;
            end
        endcase
    end

endmodule

`default_nettype wire

test/control/tb_control.sv
`default_nettype none
`include "tiny_risc.svh"

module tb_control;

    // DUT inputs
    logic [6:0] tb_opcode;
    logic [2:0] tb_funct3;
    logic [6:0] tb_funct7;

    // DUT outputs
    logic       tb_reg_write;
    logic       tb_alu_src;
    logic [1:0] tb_mem_to_reg;
    logic       tb_mem_write;
    logic       tb_mem_read;
    logic       tb_branch;
    logic       tb_jump;
    logic [3:0] tb_alu_control;

    integer     fail_cnt = 0;
    integer     compare_cnt = 0;

    // Instantiate DUT
    control i_control (
        .opcode(tb_opcode),
        .funct3(tb_funct3),
        .funct7(tb_funct7),
        .reg_write(tb_reg_write),
        .alu_src(tb_alu_src),
        .mem_to_reg(tb_mem_to_reg),
        .mem_write(tb_mem_write),
        .mem_read(tb_mem_read),
        .branch(tb_branch),
        .jump(tb_jump),
        .alu_control(tb_alu_control)
    );

    // Setup waveform dump
    initial begin
        $dumpfile("tb_control.vcd");
        $dumpvars(0, tb_control);
    end

    // Helper task to check outputs
    task check_ctrl(
        input logic [6:0] op,
        input logic [2:0] f3,
        input logic [6:0] f7,
        input logic       exp_reg_write,
        input logic       exp_alu_src,
        input logic [1:0] exp_mem_to_reg,
        input logic       exp_mem_write,
        input logic       exp_mem_read,
        input logic       exp_branch,
        input logic       exp_jump,
        input logic [3:0] exp_alu_control,
        input string      test_name
    );
        tb_opcode = op;
        tb_funct3 = f3;
        tb_funct7 = f7;
        #1; // Wait for logic propagation

        compare_cnt = compare_cnt + 1;
        if (tb_reg_write !== exp_reg_write ||
            tb_alu_src !== exp_alu_src ||
            tb_mem_to_reg !== exp_mem_to_reg ||
            tb_mem_write !== exp_mem_write ||
            tb_mem_read !== exp_mem_read ||
            tb_branch !== exp_branch ||
            tb_jump !== exp_jump ||
            tb_alu_control !== exp_alu_control) begin
            
            fail_cnt = fail_cnt + 1;
            $display("FAIL: %s", test_name);
            $display("  Inputs  : opcode=%b(7'h%h), funct3=%b, funct7=%b", op, op, f3, f7);
            $display("  Expected: reg_write=%b, alu_src=%b, mem_to_reg=%b, mem_write=%b, mem_read=%b, branch=%b, jump=%b, alu_ctrl=4'h%h",
                     exp_reg_write, exp_alu_src, exp_mem_to_reg, exp_mem_write, exp_mem_read, exp_branch, exp_jump, exp_alu_control);
            $display("  Actual  : reg_write=%b, alu_src=%b, mem_to_reg=%b, mem_write=%b, mem_read=%b, branch=%b, jump=%b, alu_ctrl=4'h%h",
                     tb_reg_write, tb_alu_src, tb_mem_to_reg, tb_mem_write, tb_mem_read, tb_branch, tb_jump, tb_alu_control);
        end else begin
            // $display("PASS: %s", test_name);
        end
    endtask

    function void display_result();
        if (fail_cnt == 0) begin
            $display("Pass: 0 errors, %d checks", compare_cnt);
        end else begin
            $display("Error: %d errors, %d checks", fail_cnt, compare_cnt);
        end
    endfunction

    initial begin
        $display("-------------------------------------------");
        $display("Starting CONTROL Testbench");
        $display("-------------------------------------------");

        // Sensible defaults
        tb_opcode = 7'b0;
        tb_funct3 = 3'b0;
        tb_funct7 = 7'b0;
        #10;

        // ==========================================
        // 1. R-Type operations (Opcode: 7'b0110011)
        // ==========================================
        $display("-- 1. R-Type checks");
        // ADD
        check_ctrl(`OPCODE_R_TYPE, 3'b000, 7'h00, 1'b1, 1'b0, 2'b00, 1'b0, 1'b0, 1'b0, 1'b0, `ALU_ADD, "R-Type ADD");
        // SUB
        check_ctrl(`OPCODE_R_TYPE, 3'b000, 7'h20, 1'b1, 1'b0, 2'b00, 1'b0, 1'b0, 1'b0, 1'b0, `ALU_SUB, "R-Type SUB");
        // SLL
        check_ctrl(`OPCODE_R_TYPE, 3'b001, 7'h00, 1'b1, 1'b0, 2'b00, 1'b0, 1'b0, 1'b0, 1'b0, `ALU_SLL, "R-Type SLL");
        // SLT
        check_ctrl(`OPCODE_R_TYPE, 3'b010, 7'h00, 1'b1, 1'b0, 2'b00, 1'b0, 1'b0, 1'b0, 1'b0, `ALU_SLT, "R-Type SLT");
        // SLTU
        check_ctrl(`OPCODE_R_TYPE, 3'b011, 7'h00, 1'b1, 1'b0, 2'b00, 1'b0, 1'b0, 1'b0, 1'b0, `ALU_SLTU, "R-Type SLTU");
        // XOR
        check_ctrl(`OPCODE_R_TYPE, 3'b100, 7'h00, 1'b1, 1'b0, 2'b00, 1'b0, 1'b0, 1'b0, 1'b0, `ALU_XOR, "R-Type XOR");
        // SRL
        check_ctrl(`OPCODE_R_TYPE, 3'b101, 7'h00, 1'b1, 1'b0, 2'b00, 1'b0, 1'b0, 1'b0, 1'b0, `ALU_SRL, "R-Type SRL");
        // SRA
        check_ctrl(`OPCODE_R_TYPE, 3'b101, 7'h20, 1'b1, 1'b0, 2'b00, 1'b0, 1'b0, 1'b0, 1'b0, `ALU_SRA, "R-Type SRA");
        // OR
        check_ctrl(`OPCODE_R_TYPE, 3'b110, 7'h00, 1'b1, 1'b0, 2'b00, 1'b0, 1'b0, 1'b0, 1'b0, `ALU_OR, "R-Type OR");
        // AND
        check_ctrl(`OPCODE_R_TYPE, 3'b111, 7'h00, 1'b1, 1'b0, 2'b00, 1'b0, 1'b0, 1'b0, 1'b0, `ALU_AND, "R-Type AND");

        // ==========================================
        // 2. I-Type ALU operations (Opcode: 7'b0010011)
        // ==========================================
        $display("-- 2. I-Type ALU checks");
        // ADDI
        check_ctrl(`OPCODE_I_TYPE, 3'b000, 7'h00, 1'b1, 1'b1, 2'b00, 1'b0, 1'b0, 1'b0, 1'b0, `ALU_ADD, "I-Type ADDI");
        // SLLI
        check_ctrl(`OPCODE_I_TYPE, 3'b001, 7'h00, 1'b1, 1'b1, 2'b00, 1'b0, 1'b0, 1'b0, 1'b0, `ALU_SLL, "I-Type SLLI");
        // SLTI
        check_ctrl(`OPCODE_I_TYPE, 3'b010, 7'h00, 1'b1, 1'b1, 2'b00, 1'b0, 1'b0, 1'b0, 1'b0, `ALU_SLT, "I-Type SLTI");
        // SLTIU
        check_ctrl(`OPCODE_I_TYPE, 3'b011, 7'h00, 1'b1, 1'b1, 2'b00, 1'b0, 1'b0, 1'b0, 1'b0, `ALU_SLTU, "I-Type SLTIU");
        // XORI
        check_ctrl(`OPCODE_I_TYPE, 3'b100, 7'h00, 1'b1, 1'b1, 2'b00, 1'b0, 1'b0, 1'b0, 1'b0, `ALU_XOR, "I-Type XORI");
        // SRLI
        check_ctrl(`OPCODE_I_TYPE, 3'b101, 7'h00, 1'b1, 1'b1, 2'b00, 1'b0, 1'b0, 1'b0, 1'b0, `ALU_SRL, "I-Type SRLI");
        // SRAI
        check_ctrl(`OPCODE_I_TYPE, 3'b101, 7'h20, 1'b1, 1'b1, 2'b00, 1'b0, 1'b0, 1'b0, 1'b0, `ALU_SRA, "I-Type SRAI");
        // ORI
        check_ctrl(`OPCODE_I_TYPE, 3'b110, 7'h00, 1'b1, 1'b1, 2'b00, 1'b0, 1'b0, 1'b0, 1'b0, `ALU_OR, "I-Type ORI");
        // ANDI
        check_ctrl(`OPCODE_I_TYPE, 3'b111, 7'h00, 1'b1, 1'b1, 2'b00, 1'b0, 1'b0, 1'b0, 1'b0, `ALU_AND, "I-Type ANDI");

        // ==========================================
        // 3. I-Type Load operations (Opcode: 7'b0000011)
        // ==========================================
        $display("-- 3. Load checks");
        check_ctrl(`OPCODE_LOAD, 3'b010, 7'h00, 1'b1, 1'b1, 2'b01, 1'b0, 1'b1, 1'b0, 1'b0, `ALU_ADD, "I-Type LW");

        // ==========================================
        // 4. S-Type Store operations (Opcode: 7'b0100011)
        // ==========================================
        $display("-- 4. Store checks");
        check_ctrl(`OPCODE_STORE, 3'b010, 7'h00, 1'b0, 1'b1, 2'b00, 1'b1, 1'b0, 1'b0, 1'b0, `ALU_ADD, "S-Type SW");

        // ==========================================
        // 5. B-Type Branch instructions (Opcode: 7'b1100011)
        // ==========================================
        $display("-- 5. Branch checks");
        // BEQ
        check_ctrl(`OPCODE_BRANCH, 3'b000, 7'h00, 1'b0, 1'b0, 2'b00, 1'b0, 1'b0, 1'b1, 1'b0, `ALU_SUB, "B-Type BEQ");
        // BNE
        check_ctrl(`OPCODE_BRANCH, 3'b001, 7'h00, 1'b0, 1'b0, 2'b00, 1'b0, 1'b0, 1'b1, 1'b0, `ALU_SUB, "B-Type BNE");
        // BLT
        check_ctrl(`OPCODE_BRANCH, 3'b100, 7'h00, 1'b0, 1'b0, 2'b00, 1'b0, 1'b0, 1'b1, 1'b0, `ALU_SLT, "B-Type BLT");
        // BGE
        check_ctrl(`OPCODE_BRANCH, 3'b101, 7'h00, 1'b0, 1'b0, 2'b00, 1'b0, 1'b0, 1'b1, 1'b0, `ALU_SLT, "B-Type BGE");
        // BLTU
        check_ctrl(`OPCODE_BRANCH, 3'b110, 7'h00, 1'b0, 1'b0, 2'b00, 1'b0, 1'b0, 1'b1, 1'b0, `ALU_SLTU, "B-Type BLTU");
        // BGEU
        check_ctrl(`OPCODE_BRANCH, 3'b111, 7'h00, 1'b0, 1'b0, 2'b00, 1'b0, 1'b0, 1'b1, 1'b0, `ALU_SLTU, "B-Type BGEU");

        // ==========================================
        // 6. J-Type JAL jump (Opcode: 7'b1101111)
        // ==========================================
        $display("-- 6. JAL checks");
        check_ctrl(`OPCODE_JAL, 3'b000, 7'h00, 1'b1, 1'b0, 2'b10, 1'b0, 1'b0, 1'b0, 1'b1, `ALU_ADD, "J-Type JAL");

        // ==========================================
        // 7. I-Type JALR jump (Opcode: 7'b1100111)
        // ==========================================
        $display("-- 7. JALR checks");
        check_ctrl(`OPCODE_JALR, 3'b000, 7'h00, 1'b1, 1'b1, 2'b10, 1'b0, 1'b0, 1'b0, 1'b1, `ALU_ADD, "I-Type JALR");

        // ==========================================
        // 8. U-Type LUI loading (Opcode: 7'b0110111)
        // ==========================================
        $display("-- 8. LUI checks");
        check_ctrl(`OPCODE_LUI, 3'b000, 7'h00, 1'b1, 1'b1, 2'b00, 1'b0, 1'b0, 1'b0, 1'b0, `ALU_LUI, "U-Type LUI");

        // ==========================================
        // 9. Invalid/Undefined Opcode (Opcode: 7'b1111111)
        // ==========================================
        $display("-- 9. Invalid opcode checks");
        check_ctrl(7'b1111111, 3'b000, 7'h00, 1'b0, 1'b0, 2'b00, 1'b0, 1'b0, 1'b0, 1'b0, `ALU_ADD, "Invalid Opcode 7'b1111111");

        $display("-------------------------------------------");
        display_result();
        $display("-------------------------------------------");

        $finish;
    end

endmodule
`default_nettype wire

test/control/tb_control.vcd
$date
	Sun Jun 28 16:13:28 2026
$end
$version
	Icarus Verilog
$end
$timescale
	1ps
$end
$scope module tb_control $end
$var wire 1 ! tb_reg_write $end
$var wire 1 " tb_mem_write $end
$var wire 2 # tb_mem_to_reg [1:0] $end
$var wire 1 $ tb_mem_read $end
$var wire 1 % tb_jump $end
$var wire 1 & tb_branch $end
$var wire 1 ' tb_alu_src $end
$var wire 4 ( tb_alu_control [3:0] $end
$var reg 3 ) tb_funct3 [2:0] $end
$var reg 7 * tb_funct7 [6:0] $end
$var reg 7 + tb_opcode [6:0] $end
$var integer 32 , compare_cnt [31:0] $end
$var integer 32 - fail_cnt [31:0] $end
$scope function display_result $end
$upscope $end
$scope module i_control $end
$var wire 3 . funct3 [2:0] $end
$var wire 7 / funct7 [6:0] $end
$var wire 7 0 opcode [6:0] $end
$var wire 1 1 funct7_5 $end
$var reg 4 2 alu_control [3:0] $end
$var reg 1 ' alu_src $end
$var reg 1 & branch $end
$var reg 1 % jump $end
$var reg 1 $ mem_read $end
$var reg 2 3 mem_to_reg [1:0] $end
$var reg 1 " mem_write $end
$var reg 1 ! reg_write $end
$upscope $end
$scope task check_ctrl $end
$var reg 4 4 exp_alu_control [3:0] $end
$var reg 1 5 exp_alu_src $end
$var reg 1 6 exp_branch $end
$var reg 1 7 exp_jump $end
$var reg 1 8 exp_mem_read $end
$var reg 2 9 exp_mem_to_reg [1:0] $end
$var reg 1 : exp_mem_write $end
$var reg 1 ; exp_reg_write $end
$var reg 3 < f3 [2:0] $end
$var reg 7 = f7 [6:0] $end
$var reg 7 > op [6:0] $end
$upscope $end
$upscope $end
$enddefinitions $end
$comment Show the parameter values. $end
$dumpall
$end
#0
$dumpvars
bx >
bx =
bx <
x;
x:
bx 9
x8
x7
x6
x5
bx 4
b0 3
b0 2
01
b0 0
b0 /
b0 .
b0 -
b0 ,
b0 +
b0 *
b0 )
b0 (
0'
0&
0%
0$
b0 #
0"
0!
$end
#10000
1!
b110011 +
b110011 0
b0 4
07
06
08
0:
b0 9
05
1;
b0 =
b0 <
b110011 >
#11000
b1 (
b1 2
1!
11
b100000 *
b100000 /
b1 4
b100000 =
b1 ,
#12000
01
b101 (
b101 2
1!
b0 *
b0 /
b1 )
b1 .
b101 4
b0 =
b1 <
b10 ,
#13000
b1000 (
b1000 2
1!
b10 )
b10 .
b1000 4
b10 <
b11 ,
#14000
b1001 (
b1001 2
1!
b11 )
b11 .
b1001 4
b11 <
b100 ,
#15000
b100 (
b100 2
1!
b100 )
b100 .
b100 4
b100 <
b101 ,
#16000
b110 (
b110 2
1!
b101 )
b101 .
b110 4
b101 <
b110 ,
#17000
b111 (
b111 2
1!
11
b100000 *
b100000 /
b111 4
b100000 =
b111 ,
#18000
01
b11 (
b11 2
1!
b0 *
b0 /
b110 )
b110 .
b11 4
b0 =
b110 <
b1000 ,
#19000
b10 (
b10 2
1!
b111 )
b111 .
b10 4
b111 <
b1001 ,
#20000
1'
b0 (
b0 2
1!
b0 )
b0 .
b10011 +
b10011 0
b0 4
15
b0 <
b10011 >
b1010 ,
#21000
b101 (
b101 2
1'
1!
b1 )
b1 .
b101 4
b1 <
b1011 ,
#22000
b1000 (
b1000 2
1'
1!
b10 )
b10 .
b1000 4
b10 <
b1100 ,
#23000
b1001 (
b1001 2
1'
1!
b11 )
b11 .
b1001 4
b11 <
b1101 ,
#24000
b100 (
b100 2
1'
1!
b100 )
b100 .
b100 4
b100 <
b1110 ,
#25000
b110 (
b110 2
1'
1!
b101 )
b101 .
b110 4
b101 <
b1111 ,
#26000
b111 (
b111 2
1'
1!
11
b100000 *
b100000 /
b111 4
b100000 =
b10000 ,
#27000
01
b11 (
b11 2
1'
1!
b0 *
b0 /
b110 )
b110 .
b11 4
b0 =
b110 <
b10001 ,
#28000
b10 (
b10 2
1'
1!
b111 )
b111 .
b10 4
b111 <
b10010 ,
#29000
1$
b1 #
b1 3
b0 (
b0 2
1'
1!
b10 )
b10 .
b11 +
b11 0
b0 4
18
b1 9
b10 <
b11 >
b10011 ,
#30000
1"
0$
b0 #
b0 3
1'
0!
b100011 +
b100011 0
08
1:
b0 9
0;
b100011 >
b10100 ,
#31000
b1 (
b1 2
1&
0"
0'
b0 )
b0 .
b1100011 +
b1100011 0
b1 4
16
0:
05
b0 <
b1100011 >
b10101 ,
#32000
b1 (
b1 2
1&
b1 )
b1 .
b1 <
b10110 ,
#33000
b1000 (
b1000 2
1&
b100 )
b100 .
b1000 4
b100 <
b10111 ,
#34000
b1000 (
b1000 2
1&
b101 )
b101 .
b101 <
b11000 ,
#35000
b1001 (
b1001 2
1&
b110 )
b110 .
b1001 4
b110 <
b11001 ,
#36000
b1001 (
b1001 2
1&
b111 )
b111 .
b111 <
b11010 ,
#37000
1%
b10 #
b10 3
1!
b0 (
b0 2
0&
b0 )
b0 .
b1101111 +
b1101111 0
b0 4
17
06
b10 9
1;
b0 <
b1101111 >
b11011 ,
#38000
1'
1%
b10 #
b10 3
1!
b1100111 +
b1100111 0
15
b1100111 >
b11100 ,
#39000
b1010 (
b1010 2
0%
b0 #
b0 3
1'
1!
b110111 +
b110111 0
b1010 4
07
b0 9
b110111 >
b11101 ,
#40000
b0 (
b0 2
0'
0!
b1111111 +
b1111111 0
b0 4
05
0;
b1111111 >
b11110 ,
#41000
b11111 ,
