src/tiny_risc.svh
`ifndef RISCV32_SVH
`define RISCV32_SVH

// ------------------------------------------------------------------
// 1. 基本設定 (データ幅とレジスタ本数)
// ------------------------------------------------------------------
`define DATA_WIDTH 32
`define REG_WIDTH 5
`define ALU_CONTROL_WIDTH 4
`define RESULT_SRC_WIDTH 2
`define OPCODE_WIDTH 7
`define FUNCT3_WIDTH 3
`define FUNCT7_WIDTH 7

// ------------------------------------------------------------------
// 2. RISC-V 命令 Opcode (7-bit: inst[6:0])
// ------------------------------------------------------------------
`define OPCODE_LOAD 7'b0000011 // LW, LH, LB (I-type Load)
`define OPCODE_I_TYPE 7'b0010011 // ADDI, SLLI, SRLI, SRAI (I-type Arith)
`define OPCODE_AUIPC 7'b0010111 // AUIPC (U-type)
`define OPCODE_STORE 7'b0100011 // SW, SH, SB (S-type Store)
`define OPCODE_R_TYPE 7'b0110011 // ADD, SUB, SLT, XOR, etc. (R-type)
`define OPCODE_LUI 7'b0110111 // LUI (U-type)
`define OPCODE_BRANCH 7'b1100011 // BEQ, BNE, BLT, BGE, etc. (B-type)
`define OPCODE_JALR 7'b1100111 // JALR (I-type Jump)
`define OPCODE_JAL 7'b1101111 // JAL (J-type Jump)
`define OPCODE_SYSTEM 7'b1110011 // ECALL, EBREAK, CSRR* (I-type System)

// ------------------------------------------------------------------
// 3. RISC-V Funct3 (3-bit: inst[14:12])
// ------------------------------------------------------------------
// R-Type & I-Type (共通・演算)
`define FUNCT3_ADD_SUB 3'b000    // ADD / SUB (R-Type)
`define FUNCT3_ADDI 3'b000    // ADDI (I-Type)
`define FUNCT3_SLL 3'b001    // SLL (R-Type)
`define FUNCT3_SLLI 3'b001    // SLLI (I-Type)
`define FUNCT3_SLT 3'b010    // SLT (R-Type)
`define FUNCT3_SLTI 3'b010    // SLTI (I-Type)
`define FUNCT3_SLTU 3'b011    // SLTU (R-Type)
`define FUNCT3_SLTIU 3'b011    // SLTIU (I-Type)
`define FUNCT3_XOR 3'b100    // XOR (R-Type)
`define FUNCT3_XORI 3'b100    // XORI (I-Type)
`define FUNCT3_SHIFT     3'b101    // SRL / SRA / SRLI / SRAI 用共通デコードプレースホルダ
`define FUNCT3_SRL_SRA 3'b101    // SRL / SRA (R-Type)
`define FUNCT3_SRAI_SRLI 3'b101    // SRAI / SRLI (I-Type)
`define FUNCT3_OR 3'b110    // OR (R-Type)
`define FUNCT3_ORI 3'b110    // ORI (I-Type)
`define FUNCT3_AND 3'b111    // AND (R-Type)
`define FUNCT3_ANDI 3'b111    // ANDI (I-Type)

// B-Type (Branch)
`define FUNCT3_BEQ 3'b000    // BEQ
`define FUNCT3_BNE 3'b001    // BNE
`define FUNCT3_BLT 3'b100    // BLT
`define FUNCT3_BGE 3'b101    // BGE
`define FUNCT3_BLTU 3'b110    // BLTU
`define FUNCT3_BGEU 3'b111    // BGEU

// ------------------------------------------------------------------
// 4. RISC-V Funct7 (7-bit: inst[31:25])
// ------------------------------------------------------------------
`define FUNCT7_ADD_SLL_SRL 7'b0000000 // ADD, SLL, SRL (R-type)
`define FUNCT7_SUB_SRA 7'b0100000 // SUB, SRA (R-type / I-type shift)
`define FUNCT7_SUB 7'b0100000 // SUB 判定用
`define FUNCT7_SRA 7'b0100000 // SRA 判定用

// ------------------------------------------------------------------
// 5. ALU 制御コード (4-bit, 制御ユニットが出力)
// ------------------------------------------------------------------
// 演算命令
`define ALU_ADD 4'h0
`define ALU_SUB 4'h1
`define ALU_AND 4'h2
`define ALU_OR 4'h3
`define ALU_XOR 4'h4
`define ALU_SLL 4'h5
`define ALU_SRL 4'h6
`define ALU_SRA 4'h7
`define ALU_SLT 4'h8
`define ALU_SLTU 4'h9
`define ALU_LUI 4'hA

// 分岐比較 (Branch)
// BEQ/BNE/BLT/BGE 命令の実行に必要な比較指示
`define BR_BEQ 4'hA // Branch Equal (A == B)
`define BR_BNE 4'hB // Branch Not Equal (A != B)
`define BR_BLT 4'hC // Branch Less Than Signed (A <s B)
`define BR_BGE 4'hD // Branch Greater Than or Equal Signed (A >=s B)
`define BR_BLTU 4'hE // Branch Less Than Unsigned (A <u B)
`define BR_BGEU 4'hF // Branch Greater Than or Equal Unsigned (A >=u B)

// ------------------------------------------------------------------
// 6. Write Back Data Source (ResultSrc: 2-bit)
// ------------------------------------------------------------------
`define RESULT_SRC_ALU 2'b00  // ALUの結果を書き込む (デフォルト)
`define RESULT_SRC_MEM 2'b01  // メモリからの読み出しデータを書き込む (Load命令用)
`define RESULT_SRC_PC4 2'b10  // PC+4の値を書き込む (JAL命令用)

`define RESULT_ALU 2'b00  // RESULT_SRC_ALU と同等 (別名)
`define RESULT_MEM 2'b01  // RESULT_SRC_MEM と同等 (別名)
`define RESULT_PC4 2'b10  // RESULT_SRC_PC4 と同等 (別名)
// 2'b11 は未定義/予約

`endif  // RISCV32_SVH

src/regfile.sv

// ====================================================================
// Module: regfile
// Description: Multi-ported 32x32 general register file.
//              Contains x0 hardwired to constant 0x0 at all times.
// ====================================================================

`default_nettype none

`include "tiny_risc.svh"

module regfile #(
    parameter XLEN = 32
) (
    input logic clock,
    input logic resetn,
    input logic we,     // Write enable

    input logic [4:0] addr_rs1,  // Read address index 1
    input logic [4:0] addr_rs2,  // Read address index 2
    input logic [4:0] addr_rd,   // Write address index

    input logic [XLEN-1:0] write_data,

    output logic [XLEN-1:0] data_rs1,
    output logic [XLEN-1:0] data_rs2
);

    // Declare 32 active general registers using low_case signal
    logic [XLEN-1:0] register_array[31:0];

    // Port reading combinations (Register x0 hardwired to zero)
    assign data_rs1 = (addr_rs1 == 5'b0) ? 32'b0 : register_array[addr_rs1];
    assign data_rs2 = (addr_rs2 == 5'b0) ? 32'b0 : register_array[addr_rs2];

    // Regfile synchronized writes
    always_ff @(posedge clock or negedge resetn) begin
        if (!resetn) begin
            // Reset registers to simple default state
            integer index;
            for (index = 0; index < 32; index = index + 1) begin
                register_array[index] <= 32'b0;
            end
        end else if (we && (addr_rd != 5'b0)) begin
            // Write incoming data only if not register zero
            register_array[addr_rd] <= write_data;
        end
    end
endmodule

`default_nettype wire

test/regfile/tb_regfile.sv

`default_nettype none

module tb_regfile;
    localparam XLEN = 32;

    // DUT (Device Under Test: register_file) の信号宣言
    reg            tb_clock;
    reg            tb_resetn;

    logic          tb_we;
    logic   [ 4:0] tb_addr_rs1;
    logic   [ 4:0] tb_addr_rs2;
    logic   [ 4:0] tb_addr_rd;
    logic   [31:0] tb_write_data;
    logic   [31:0] tb_data_rs1;
    logic   [31:0] tb_data_rs2;

    integer        fail_cnt = 0;
    integer        compare_cnt = 0;

    // テスト対象モジュールのインスタンス化
    regfile #(
        .XLEN(XLEN)
    ) i_regfile (
        .clock(tb_clock),
        .resetn(tb_resetn),
        .we(tb_we),
        .addr_rs1(tb_addr_rs1),
        .addr_rs2(tb_addr_rs2),
        .addr_rd(tb_addr_rd),
        .write_data(tb_write_data),
        .data_rs1(tb_data_rs1),
        .data_rs2(tb_data_rs2)
    );

    // クロック生成 (50%デューティサイクル)
    always #5 tb_clock = ~tb_clock;

    initial begin
        // Set up for waveform dumping
        $dumpfile("tb_regfile.vcd");
        $dumpvars(0, tb_regfile);

        for (int i = 0; i < XLEN; i = i + 1) begin
            $dumpvars(0, tb_regfile.i_regfile.register_array[i]);
        end
    end

    task compare(input logic [XLEN-1:0] exp, input logic [XLEN-1:0] act,
                 input int addr);
        compare_cnt = compare_cnt + 1;
        if (exp != act) begin
            fail_cnt = fail_cnt + 1;
            $display("Error: Expected %b, Actually %b (Addr: %d) at time %t",
                     exp, act, addr, $time);
        end else begin
            // $display("Pass: Expected %b, Actually %b", exp, act);
        end
    endtask

    function void display_result();
        if (0 == fail_cnt) begin
            $display("Pass: 0 errors, %d checks", compare_cnt);
        end else begin
            $display("Error: %d errors, %d checks", fail_cnt, compare_cnt);
        end
    endfunction

    initial begin
        tb_resetn = 1;
        #10 tb_clock = 0;
        tb_resetn = 0;
        tb_we = 0;
        tb_addr_rs1 = 5'd0;
        tb_addr_rs2 = 5'd0;
        tb_addr_rd = 5'd0;

        #10 tb_resetn = 1;
        @(posedge tb_clock);

        $display("-- Clear check");
        fail_cnt = 0;
        compare_cnt = 0;
        for (int i = 0; i < 32; i = i + 1) begin
            tb_addr_rs1 = i;
            @(posedge tb_clock);

            compare(32'd0, tb_data_rs1, i);
        end
        display_result();

        $display("-- Write check (x0 exclude)");
        fail_cnt = 0;
        compare_cnt = 0;
        for (int i = 1; i < 32; i = i + 1) begin
            tb_addr_rs1 = i;
            tb_addr_rd = i;
            tb_we = 1;
            tb_write_data = {(XLEN / 2) {2'b10}};
            @(posedge tb_clock);
            tb_we = 0;

            @(posedge tb_clock);

            compare(tb_write_data, tb_data_rs1, i);
        end
        display_result();

        $display("-- x0 check");
        fail_cnt = 0;
        compare_cnt = 0;
        tb_addr_rd = 5'd0;
        tb_addr_rs1 = 5'd0;
        tb_we = 1;
        tb_write_data = {(XLEN / 2) {2'b10}};
        @(posedge tb_clock);
        tb_we = 0;

        @(posedge tb_clock);

        compare(32'd0, tb_data_rs1, 5'd0);
        display_result();

        $display("-- Simultaneous Read check");
        fail_cnt = 0;
        compare_cnt = 0;
        // rs1 and rs2 read different registers simultaneously
        tb_addr_rs1 = 5'd5;
        tb_addr_rs2 = 5'd10;
        #1;
        compare({(XLEN / 2) {2'b10}}, tb_data_rs1, 5'd5);
        compare({(XLEN / 2) {2'b10}}, tb_data_rs2, 5'd10);

        // rs1 and rs2 read the same register simultaneously
        tb_addr_rs1 = 5'd8;
        tb_addr_rs2 = 5'd8;
        #1;
        compare({(XLEN / 2) {2'b10}}, tb_data_rs1, 5'd8);
        compare({(XLEN / 2) {2'b10}}, tb_data_rs2, 5'd8);
        display_result();

        $display("-- Simultaneous Write/Read check");
        fail_cnt = 0;
        compare_cnt = 0;
        // Write to x15, and simultaneously read x15 via rs1, and x16 via rs2
        tb_addr_rd = 5'd15;
        tb_write_data = 32'h55555555;
        tb_we = 1;
        tb_addr_rs1 = 5'd15;
        tb_addr_rs2 = 5'd16;

        // Before posedge clock, rs1 and rs2 should output old values
        #1;
        compare({(XLEN / 2) {2'b10}}, tb_data_rs1, 5'd15);
        compare({(XLEN / 2) {2'b10}}, tb_data_rs2, 5'd16);

        // Trigger write at posedge clock
        @(posedge tb_clock);

        // After posedge clock, rs1 (x15) should output the newly written value
        // rs2 (x16) should still output the old value
        #1;
        compare(32'h55555555, tb_data_rs1, 5'd15);
        compare({(XLEN / 2) {2'b10}}, tb_data_rs2, 5'd16);

        tb_we = 0;
        @(posedge tb_clock);
        display_result();

        $finish;
    end
endmodule

test/regfile/tb_regfile.vcd
$date
	Sun Jun 28 15:43:52 2026
$end
$version
	Icarus Verilog
$end
$timescale
	1ps
$end
$scope module tb_regfile $end
$var wire 32 ! tb_data_rs2 [31:0] $end
$var wire 32 " tb_data_rs1 [31:0] $end
$var parameter 32 # XLEN $end
$var reg 5 $ tb_addr_rd [4:0] $end
$var reg 5 % tb_addr_rs1 [4:0] $end
$var reg 5 & tb_addr_rs2 [4:0] $end
$var reg 1 ' tb_clock $end
$var reg 1 ( tb_resetn $end
$var reg 1 ) tb_we $end
$var reg 32 * tb_write_data [31:0] $end
$var integer 32 + compare_cnt [31:0] $end
$var integer 32 , fail_cnt [31:0] $end
$scope function display_result $end
$upscope $end
$scope module i_regfile $end
$var wire 5 - addr_rd [4:0] $end
$var wire 5 . addr_rs1 [4:0] $end
$var wire 5 / addr_rs2 [4:0] $end
$var wire 1 ' clock $end
$var wire 1 ( resetn $end
$var wire 1 ) we $end
$var wire 32 0 write_data [31:0] $end
$var wire 32 1 data_rs2 [31:0] $end
$var wire 32 2 data_rs1 [31:0] $end
$var parameter 32 3 XLEN $end
$scope begin $unm_blk_11 $end
$var integer 32 4 index [31:0] $end
$upscope $end
$upscope $end
$scope begin $ivl_for_loop0 $end
$var integer 32 5 i [31:0] $end
$upscope $end
$scope begin $ivl_for_loop1 $end
$var integer 32 6 i [31:0] $end
$upscope $end
$scope begin $ivl_for_loop2 $end
$var integer 32 7 i [31:0] $end
$upscope $end
$scope task compare $end
$var reg 32 8 act [31:0] $end
$var reg 32 9 exp [31:0] $end
$var integer 32 : addr [31:0] $end
$upscope $end
$upscope $end
$scope module tb_regfile $end
$scope module i_regfile $end
$var reg 32 ; \register_array[0] [31:0] $end
$upscope $end
$upscope $end
$scope module tb_regfile $end
$scope module i_regfile $end
$var reg 32 < \register_array[1] [31:0] $end
$upscope $end
$upscope $end
$scope module tb_regfile $end
$scope module i_regfile $end
$var reg 32 = \register_array[2] [31:0] $end
$upscope $end
$upscope $end
$scope module tb_regfile $end
$scope module i_regfile $end
$var reg 32 > \register_array[3] [31:0] $end
$upscope $end
$upscope $end
$scope module tb_regfile $end
$scope module i_regfile $end
$var reg 32 ? \register_array[4] [31:0] $end
$upscope $end
$upscope $end
$scope module tb_regfile $end
$scope module i_regfile $end
$var reg 32 @ \register_array[5] [31:0] $end
$upscope $end
$upscope $end
$scope module tb_regfile $end
$scope module i_regfile $end
$var reg 32 A \register_array[6] [31:0] $end
$upscope $end
$upscope $end
$scope module tb_regfile $end
$scope module i_regfile $end
$var reg 32 B \register_array[7] [31:0] $end
$upscope $end
$upscope $end
$scope module tb_regfile $end
$scope module i_regfile $end
$var reg 32 C \register_array[8] [31:0] $end
$upscope $end
$upscope $end
$scope module tb_regfile $end
$scope module i_regfile $end
$var reg 32 D \register_array[9] [31:0] $end
$upscope $end
$upscope $end
$scope module tb_regfile $end
$scope module i_regfile $end
$var reg 32 E \register_array[10] [31:0] $end
$upscope $end
$upscope $end
$scope module tb_regfile $end
$scope module i_regfile $end
$var reg 32 F \register_array[11] [31:0] $end
$upscope $end
$upscope $end
$scope module tb_regfile $end
$scope module i_regfile $end
$var reg 32 G \register_array[12] [31:0] $end
$upscope $end
$upscope $end
$scope module tb_regfile $end
$scope module i_regfile $end
$var reg 32 H \register_array[13] [31:0] $end
$upscope $end
$upscope $end
$scope module tb_regfile $end
$scope module i_regfile $end
$var reg 32 I \register_array[14] [31:0] $end
$upscope $end
$upscope $end
$scope module tb_regfile $end
$scope module i_regfile $end
$var reg 32 J \register_array[15] [31:0] $end
$upscope $end
$upscope $end
$scope module tb_regfile $end
$scope module i_regfile $end
$var reg 32 K \register_array[16] [31:0] $end
$upscope $end
$upscope $end
$scope module tb_regfile $end
$scope module i_regfile $end
$var reg 32 L \register_array[17] [31:0] $end
$upscope $end
$upscope $end
$scope module tb_regfile $end
$scope module i_regfile $end
$var reg 32 M \register_array[18] [31:0] $end
$upscope $end
$upscope $end
$scope module tb_regfile $end
$scope module i_regfile $end
$var reg 32 N \register_array[19] [31:0] $end
$upscope $end
$upscope $end
$scope module tb_regfile $end
$scope module i_regfile $end
$var reg 32 O \register_array[20] [31:0] $end
$upscope $end
$upscope $end
$scope module tb_regfile $end
$scope module i_regfile $end
$var reg 32 P \register_array[21] [31:0] $end
$upscope $end
$upscope $end
$scope module tb_regfile $end
$scope module i_regfile $end
$var reg 32 Q \register_array[22] [31:0] $end
$upscope $end
$upscope $end
$scope module tb_regfile $end
$scope module i_regfile $end
$var reg 32 R \register_array[23] [31:0] $end
$upscope $end
$upscope $end
$scope module tb_regfile $end
$scope module i_regfile $end
$var reg 32 S \register_array[24] [31:0] $end
$upscope $end
$upscope $end
$scope module tb_regfile $end
$scope module i_regfile $end
$var reg 32 T \register_array[25] [31:0] $end
$upscope $end
$upscope $end
$scope module tb_regfile $end
$scope module i_regfile $end
$var reg 32 U \register_array[26] [31:0] $end
$upscope $end
$upscope $end
$scope module tb_regfile $end
$scope module i_regfile $end
$var reg 32 V \register_array[27] [31:0] $end
$upscope $end
$upscope $end
$scope module tb_regfile $end
$scope module i_regfile $end
$var reg 32 W \register_array[28] [31:0] $end
$upscope $end
$upscope $end
$scope module tb_regfile $end
$scope module i_regfile $end
$var reg 32 X \register_array[29] [31:0] $end
$upscope $end
$upscope $end
$scope module tb_regfile $end
$scope module i_regfile $end
$var reg 32 Y \register_array[30] [31:0] $end
$upscope $end
$upscope $end
$scope module tb_regfile $end
$scope module i_regfile $end
$var reg 32 Z \register_array[31] [31:0] $end
$upscope $end
$upscope $end
$enddefinitions $end
$comment Show the parameter values. $end
$dumpall
b100000 3
b100000 #
$end
#0
$dumpvars
bx Z
bx Y
bx X
bx W
bx V
bx U
bx T
bx S
bx R
bx Q
bx P
bx O
bx N
bx M
bx L
bx K
bx J
bx I
bx H
bx G
bx F
bx E
bx D
bx C
bx B
bx A
bx @
bx ?
bx >
bx =
bx <
bx ;
b0 :
bx 9
bx 8
b0 7
b0 6
b100000 5
bx 4
bx 2
bx 1
bx 0
bx /
bx .
bx -
b0 ,
b0 +
bx *
x)
1(
x'
bx &
bx %
bx $
bx "
bx !
$end
#10000
b0 Z
b0 Y
b0 X
b0 W
b0 V
b0 U
b0 T
b0 S
b0 R
b0 Q
b0 P
b0 O
b0 N
b0 M
b0 L
b0 K
b0 J
b0 I
b0 H
b0 G
b0 F
b0 E
b0 D
b0 C
b0 B
b0 A
b0 @
b0 ?
b0 >
b0 =
b0 <
b0 ;
b0 !
b0 1
b0 "
b0 2
b100000 4
b0 $
b0 -
b0 &
b0 /
b0 %
b0 .
0)
0(
1'
#15000
0'
#20000
1'
1(
#25000
0'
#30000
b1 %
b1 .
b1 6
b1 +
b0 8
b0 9
1'
#35000
0'
#40000
b10 %
b10 .
b10 6
b10 +
b1 :
1'
#45000
0'
#50000
b11 %
b11 .
b11 6
b11 +
b10 :
1'
#55000
0'
#60000
b100 %
b100 .
b100 6
b100 +
b11 :
1'
#65000
0'
#70000
b101 %
b101 .
b101 6
b101 +
b100 :
1'
#75000
0'
#80000
b110 %
b110 .
b110 6
b110 +
b101 :
1'
#85000
0'
#90000
b111 %
b111 .
b111 6
b111 +
b110 :
1'
#95000
0'
#100000
b1000 %
b1000 .
b1000 6
b1000 +
b111 :
1'
#105000
0'
#110000
b1001 %
b1001 .
b1001 6
b1001 +
b1000 :
1'
#115000
0'
#120000
b1010 %
b1010 .
b1010 6
b1010 +
b1001 :
1'
#125000
0'
#130000
b1011 %
b1011 .
b1011 6
b1011 +
b1010 :
1'
#135000
0'
#140000
b1100 %
b1100 .
b1100 6
b1100 +
b1011 :
1'
#145000
0'
#150000
b1101 %
b1101 .
b1101 6
b1101 +
b1100 :
1'
#155000
0'
#160000
b1110 %
b1110 .
b1110 6
b1110 +
b1101 :
1'
#165000
0'
#170000
b1111 %
b1111 .
b1111 6
b1111 +
b1110 :
1'
#175000
0'
#180000
b10000 %
b10000 .
b10000 6
b10000 +
b1111 :
1'
#185000
0'
#190000
b10001 %
b10001 .
b10001 6
b10001 +
b10000 :
1'
#195000
0'
#200000
b10010 %
b10010 .
b10010 6
b10010 +
b10001 :
1'
#205000
0'
#210000
b10011 %
b10011 .
b10011 6
b10011 +
b10010 :
1'
#215000
0'
#220000
b10100 %
b10100 .
b10100 6
b10100 +
b10011 :
1'
#225000
0'
#230000
b10101 %
b10101 .
b10101 6
b10101 +
b10100 :
1'
#235000
0'
#240000
b10110 %
b10110 .
b10110 6
b10110 +
b10101 :
1'
#245000
0'
#250000
b10111 %
b10111 .
b10111 6
b10111 +
b10110 :
1'
#255000
0'
#260000
b11000 %
b11000 .
b11000 6
b11000 +
b10111 :
1'
#265000
0'
#270000
b11001 %
b11001 .
b11001 6
b11001 +
b11000 :
1'
#275000
0'
#280000
b11010 %
b11010 .
b11010 6
b11010 +
b11001 :
1'
#285000
0'
#290000
b11011 %
b11011 .
b11011 6
b11011 +
b11010 :
1'
#295000
0'
#300000
b11100 %
b11100 .
b11100 6
b11100 +
b11011 :
1'
#305000
0'
#310000
b11101 %
b11101 .
b11101 6
b11101 +
b11100 :
1'
#315000
0'
#320000
b11110 %
b11110 .
b11110 6
b11110 +
b11101 :
1'
#325000
0'
#330000
b11111 %
b11111 .
b11111 6
b11111 +
b11110 :
1'
#335000
0'
#340000
b10101010101010101010101010101010 "
b10101010101010101010101010101010 2
b10101010101010101010101010101010 <
b10101010101010101010101010101010 *
b10101010101010101010101010101010 0
1)
b1 $
b1 -
b1 %
b1 .
b1 7
b100000 6
b0 +
b11111 :
1'
#345000
0'
#350000
0)
1'
#355000
0'
#360000
b10101010101010101010101010101010 =
b10101010101010101010101010101010 "
b10101010101010101010101010101010 2
1)
b10 $
b10 -
b10 %
b10 .
b10 7
b1 +
b1 :
b10101010101010101010101010101010 8
b10101010101010101010101010101010 9
1'
#365000
0'
#370000
0)
1'
#375000
0'
#380000
b10101010101010101010101010101010 >
b10101010101010101010101010101010 "
b10101010101010101010101010101010 2
1)
b11 $
b11 -
b11 %
b11 .
b11 7
b10 +
b10 :
1'
#385000
0'
#390000
0)
1'
#395000
0'
#400000
b10101010101010101010101010101010 ?
b10101010101010101010101010101010 "
b10101010101010101010101010101010 2
1)
b100 $
b100 -
b100 %
b100 .
b100 7
b11 +
b11 :
1'
#405000
0'
#410000
0)
1'
#415000
0'
#420000
b10101010101010101010101010101010 @
b10101010101010101010101010101010 "
b10101010101010101010101010101010 2
1)
b101 $
b101 -
b101 %
b101 .
b101 7
b100 +
b100 :
1'
#425000
0'
#430000
0)
1'
#435000
0'
#440000
b10101010101010101010101010101010 A
b10101010101010101010101010101010 "
b10101010101010101010101010101010 2
1)
b110 $
b110 -
b110 %
b110 .
b110 7
b101 +
b101 :
1'
#445000
0'
#450000
0)
1'
#455000
0'
#460000
b10101010101010101010101010101010 B
b10101010101010101010101010101010 "
b10101010101010101010101010101010 2
1)
b111 $
b111 -
b111 %
b111 .
b111 7
b110 +
b110 :
1'
#465000
0'
#470000
0)
1'
#475000
0'
#480000
b10101010101010101010101010101010 C
b10101010101010101010101010101010 "
b10101010101010101010101010101010 2
1)
b1000 $
b1000 -
b1000 %
b1000 .
b1000 7
b111 +
b111 :
1'
#485000
0'
#490000
0)
1'
#495000
0'
#500000
b10101010101010101010101010101010 D
b10101010101010101010101010101010 "
b10101010101010101010101010101010 2
1)
b1001 $
b1001 -
b1001 %
b1001 .
b1001 7
b1000 +
b1000 :
1'
#505000
0'
#510000
0)
1'
#515000
0'
#520000
b10101010101010101010101010101010 E
b10101010101010101010101010101010 "
b10101010101010101010101010101010 2
1)
b1010 $
b1010 -
b1010 %
b1010 .
b1010 7
b1001 +
b1001 :
1'
#525000
0'
#530000
0)
1'
#535000
0'
#540000
b10101010101010101010101010101010 F
b10101010101010101010101010101010 "
b10101010101010101010101010101010 2
1)
b1011 $
b1011 -
b1011 %
b1011 .
b1011 7
b1010 +
b1010 :
1'
#545000
0'
#550000
0)
1'
#555000
0'
#560000
b10101010101010101010101010101010 G
b10101010101010101010101010101010 "
b10101010101010101010101010101010 2
1)
b1100 $
b1100 -
b1100 %
b1100 .
b1100 7
b1011 +
b1011 :
1'
#565000
0'
#570000
0)
1'
#575000
0'
#580000
b10101010101010101010101010101010 H
b10101010101010101010101010101010 "
b10101010101010101010101010101010 2
1)
b1101 $
b1101 -
b1101 %
b1101 .
b1101 7
b1100 +
b1100 :
1'
#585000
0'
#590000
0)
1'
#595000
0'
#600000
b10101010101010101010101010101010 I
b10101010101010101010101010101010 "
b10101010101010101010101010101010 2
1)
b1110 $
b1110 -
b1110 %
b1110 .
b1110 7
b1101 +
b1101 :
1'
#605000
0'
#610000
0)
1'
#615000
0'
#620000
b10101010101010101010101010101010 J
b10101010101010101010101010101010 "
b10101010101010101010101010101010 2
1)
b1111 $
b1111 -
b1111 %
b1111 .
b1111 7
b1110 +
b1110 :
1'
#625000
0'
#630000
0)
1'
#635000
0'
#640000
b10101010101010101010101010101010 K
b10101010101010101010101010101010 "
b10101010101010101010101010101010 2
1)
b10000 $
b10000 -
b10000 %
b10000 .
b10000 7
b1111 +
b1111 :
1'
#645000
0'
#650000
0)
1'
#655000
0'
#660000
b10101010101010101010101010101010 L
b10101010101010101010101010101010 "
b10101010101010101010101010101010 2
1)
b10001 $
b10001 -
b10001 %
b10001 .
b10001 7
b10000 +
b10000 :
1'
#665000
0'
#670000
0)
1'
#675000
0'
#680000
b10101010101010101010101010101010 M
b10101010101010101010101010101010 "
b10101010101010101010101010101010 2
1)
b10010 $
b10010 -
b10010 %
b10010 .
b10010 7
b10001 +
b10001 :
1'
#685000
0'
#690000
0)
1'
#695000
0'
#700000
b10101010101010101010101010101010 N
b10101010101010101010101010101010 "
b10101010101010101010101010101010 2
1)
b10011 $
b10011 -
b10011 %
b10011 .
b10011 7
b10010 +
b10010 :
1'
#705000
0'
#710000
0)
1'
#715000
0'
#720000
b10101010101010101010101010101010 O
b10101010101010101010101010101010 "
b10101010101010101010101010101010 2
1)
b10100 $
b10100 -
b10100 %
b10100 .
b10100 7
b10011 +
b10011 :
1'
#725000
0'
#730000
0)
1'
#735000
0'
#740000
b10101010101010101010101010101010 P
b10101010101010101010101010101010 "
b10101010101010101010101010101010 2
1)
b10101 $
b10101 -
b10101 %
b10101 .
b10101 7
b10100 +
b10100 :
1'
#745000
0'
#750000
0)
1'
#755000
0'
#760000
b10101010101010101010101010101010 Q
b10101010101010101010101010101010 "
b10101010101010101010101010101010 2
1)
b10110 $
b10110 -
b10110 %
b10110 .
b10110 7
b10101 +
b10101 :
1'
#765000
0'
#770000
0)
1'
#775000
0'
#780000
b10101010101010101010101010101010 R
b10101010101010101010101010101010 "
b10101010101010101010101010101010 2
1)
b10111 $
b10111 -
b10111 %
b10111 .
b10111 7
b10110 +
b10110 :
1'
#785000
0'
#790000
0)
1'
#795000
0'
#800000
b10101010101010101010101010101010 S
b10101010101010101010101010101010 "
b10101010101010101010101010101010 2
1)
b11000 $
b11000 -
b11000 %
b11000 .
b11000 7
b10111 +
b10111 :
1'
#805000
0'
#810000
0)
1'
#815000
0'
#820000
b10101010101010101010101010101010 T
b10101010101010101010101010101010 "
b10101010101010101010101010101010 2
1)
b11001 $
b11001 -
b11001 %
b11001 .
b11001 7
b11000 +
b11000 :
1'
#825000
0'
#830000
0)
1'
#835000
0'
#840000
b10101010101010101010101010101010 U
b10101010101010101010101010101010 "
b10101010101010101010101010101010 2
1)
b11010 $
b11010 -
b11010 %
b11010 .
b11010 7
b11001 +
b11001 :
1'
#845000
0'
#850000
0)
1'
#855000
0'
#860000
b10101010101010101010101010101010 V
b10101010101010101010101010101010 "
b10101010101010101010101010101010 2
1)
b11011 $
b11011 -
b11011 %
b11011 .
b11011 7
b11010 +
b11010 :
1'
#865000
0'
#870000
0)
1'
#875000
0'
#880000
b10101010101010101010101010101010 W
b10101010101010101010101010101010 "
b10101010101010101010101010101010 2
1)
b11100 $
b11100 -
b11100 %
b11100 .
b11100 7
b11011 +
b11011 :
1'
#885000
0'
#890000
0)
1'
#895000
0'
#900000
b10101010101010101010101010101010 X
b10101010101010101010101010101010 "
b10101010101010101010101010101010 2
1)
b11101 $
b11101 -
b11101 %
b11101 .
b11101 7
b11100 +
b11100 :
1'
#905000
0'
#910000
0)
1'
#915000
0'
#920000
b10101010101010101010101010101010 Y
b10101010101010101010101010101010 "
b10101010101010101010101010101010 2
1)
b11110 $
b11110 -
b11110 %
b11110 .
b11110 7
b11101 +
b11101 :
1'
#925000
0'
#930000
0)
1'
#935000
0'
#940000
b10101010101010101010101010101010 Z
b10101010101010101010101010101010 "
b10101010101010101010101010101010 2
1)
b11111 $
b11111 -
b11111 %
b11111 .
b11111 7
b11110 +
b11110 :
1'
#945000
0'
#950000
0)
1'
#955000
0'
#960000
b0 "
b0 2
1)
b0 %
b0 .
b0 $
b0 -
b100000 7
b0 +
b11111 :
1'
#965000
0'
#970000
0)
1'
#975000
0'
#980000
b10101010101010101010101010101010 !
b10101010101010101010101010101010 1
b10101010101010101010101010101010 "
b10101010101010101010101010101010 2
b1010 &
b1010 /
b101 %
b101 .
b0 +
b0 :
b0 8
b0 9
1'
#981000
b1000 &
b1000 /
b1000 %
b1000 .
b10 +
b1010 :
b10101010101010101010101010101010 8
b10101010101010101010101010101010 9
#982000
b10000 &
b10000 /
b1111 %
b1111 .
1)
b1010101010101010101010101010101 *
b1010101010101010101010101010101 0
b1111 $
b1111 -
b0 +
b1000 :
#983000
b10 +
b10000 :
#985000
0'
#990000
b1010101010101010101010101010101 "
b1010101010101010101010101010101 2
b1010101010101010101010101010101 J
1'
#991000
0)
b100 +
b10000 :
b10101010101010101010101010101010 8
b10101010101010101010101010101010 9
